pyrituals/__init__.py
pyrituals/py.typed
pyrituals-0.0.6.dist-info/LICENSE
pyrituals-0.0.6.dist-info/METADATA
pyrituals-0.0.6.dist-info/WHEEL
pyrituals-0.0.6.dist-info/top_level.txt
pyrituals-0.0.6.dist-info/RECORD
