Metadata-Version: 2.1
Name: pyrituals
Version: 0.0.6
Summary: Async Python wrapper for the Rituals Perfume Genie API
Home-page: https://github.com/milanmeu/pyrituals
Author: Milan Meulemans
Author-email: milan.meulemans@live.be
Maintainer: Milan Meulemans
Maintainer-email: milan.meulemans@live.be
License: GPLv3
Project-URL: Say Thanks!, https://saythanks.io/to/milan.meulemans@live.be
Project-URL: Bug Tracker, https://github.com/milanmeu/pyrituals/issues
Project-URL: Source Code, https://github.com/milanmeu/pyrituals
Project-URL: Documentation, https://github.com/milanmeu/pyrituals/blob/main/README.md
Keywords: rituals,perfume,genie
Platform: UNKNOWN
Classifier: Programming Language :: Python :: 3
Classifier: License :: OSI Approved :: GNU General Public License v3 (GPLv3)
Classifier: Operating System :: OS Independent
Requires-Python: >=3.8
License-File: LICENSE
Requires-Dist: aiohttp
